pyinstrument_flame/__init__.py
pyinstrument_flame/flamegraph.py
pyinstrument_flame/flamegraphrenderer.py
pyinstrument_flame/vendor/flamegraph.pl
pyinstrument_flame-1.0.2.dist-info/DESCRIPTION.rst
pyinstrument_flame-1.0.2.dist-info/METADATA
pyinstrument_flame-1.0.2.dist-info/RECORD
pyinstrument_flame-1.0.2.dist-info/WHEEL
pyinstrument_flame-1.0.2.dist-info/metadata.json
pyinstrument_flame-1.0.2.dist-info/top_level.txt
