Metadata-Version: 2.0
Name: pyinstrument-flame
Version: 1.0.2
Summary: An interactive SVG Flame Chart Renderer for pyinstrument.
Home-page: UNKNOWN
Author: Christian Stuart
Author-email: me@cjstuart.nl
License: UNKNOWN
Platform: UNKNOWN
Classifier: Programming Language :: Python :: 3
Classifier: License :: OSI Approved :: MIT License
Classifier: Operating System :: OS Independent 
Classifier: Topic :: Software Development :: Debuggers
Classifier: Topic :: Software Development :: Testing
Classifier: Environment :: Web Environment
